zyk/__init__.py
zyk/lms/__init__.py
zyk/lms/config.py
zyk/lms/caching/__init__.py
zyk/lms/caching/constants.py
zyk/lms/caching/dbs.py
zyk/lms/caching/ephemeral.py
zyk/lms/caching/handler.py
zyk/lms/caching/initialize.py
zyk/lms/caching/persistent.py
zyk/lms/core/__init__.py
zyk/lms/core/all.py
zyk/lms/core/exceptions.py
zyk/lms/core/main.py
zyk/lms/core/vendor_clients.py
zyk/lms/cost/__init__.py
zyk/lms/cost/monitor.py
zyk/lms/cost/statefulness.py
zyk/lms/structured_outputs/__init__.py
zyk/lms/structured_outputs/handler.py
zyk/lms/structured_outputs/inject.py
zyk/lms/structured_outputs/rehabilitate.py
zyk/lms/vendors/__init__.py
zyk/lms/vendors/base.py
zyk/lms/vendors/constants.py
zyk/lms/vendors/openai_standard.py
zyk/lms/vendors/retries.py
zyk/lms/vendors/core/__init__.py
zyk/lms/vendors/core/anthropic_api.py
zyk/lms/vendors/core/gemini_api.py
zyk/lms/vendors/core/openai_api.py
zyk/lms/vendors/local/__init__.py
zyk/lms/vendors/local/ollama.py
zyk/lms/vendors/supported/__init__.py
zyk/lms/vendors/supported/deepseek.py
zyk/lms/vendors/supported/together.py
zyk-0.2.54.dist-info/LICENSE
zyk-0.2.54.dist-info/METADATA
zyk-0.2.54.dist-info/WHEEL
zyk-0.2.54.dist-info/top_level.txt
zyk-0.2.54.dist-info/RECORD
