Metadata-Version: 2.2
Name: zyk
Version: 0.2.54
Summary: Simple LM api wrappers for production
Home-page: https://github.com/JoshuaPurtell/jazyk
Author: Josh Purtell
Author-email: Josh Purtell <jmvpurtell@gmail.com>
License: MIT License
Project-URL: Homepage, https://github.com/JoshuaPurtell/jazyk
Keywords: zyk
Classifier: License :: OSI Approved :: MIT License
Classifier: Programming Language :: Python
Classifier: Programming Language :: Python :: 3
Requires-Python: >=3.10
License-File: LICENSE
Requires-Dist: openai
Requires-Dist: pydantic
Requires-Dist: diskcache
Requires-Dist: backoff>=2.2.1
Requires-Dist: anthropic>=0.34.2
Requires-Dist: google>=3.0.0
Requires-Dist: google-generativeai>=0.8.1
Requires-Dist: together>=1.2.12
Requires-Dist: langfuse>=2.56.1
Requires-Dist: synth-sdk==0.3.0
Requires-Dist: datasets>=3.2.0
Dynamic: author
Dynamic: home-page
